{
 "schema": 1,
 "date": "2026-07-12",
 "generated_at": "2026-07-12T06:18:08-04:00",
 "generated_by": "briefing-build v3.0.0 (Dashboards/briefing-build.md)",
 "signals_generated_at": "2026-07-12T10:07:45Z",
 "stitch_generated_at": "",
 "source_extract": "2026-07-10T09:15:01Z",
 "meta_notes": "stitch feed absent (Tier 2 Make.com not set up) — shortlist from in-group signals; source extract 2026-07-10 ~2d old at build, views/ages as of extract; news scan ran (2 searches) — no verifiable ≤7d major story, news empty by rule",
 "menu_lines": [
  "skin-cancer-or-not 5s quizzes (231× · 1%) [watch](https://www.tiktok.com/@dr.derm.love/video/7659477254749031710)",
  "glass-skin routines (YOURS — superviral TT+IG · ♥ gold) [watch](https://www.tiktok.com/@drabby6/video/7659893560606477599)",
  "doctors' 'never for my own kids' lists (1% · ♥) [watch](https://www.instagram.com/p/DalKr5PgSm1/)",
  "derm-rates product tier lists (35× · ♥) [watch](https://www.tiktok.com/@dermguru/video/7659471945418771743)",
  "sunscreen-substitution myths (125× · ♥) [watch](https://www.instagram.com/p/DaX_HEcOs-5/)"
 ],
 "themes": [
  {
   "name": "Skin-cancer-or-not 5-second quizzes",
   "heat": 3,
   "receipt": "8 quiz breakouts (TT) · one creator machine-gunning · 7.5M combined · three 1% badges",
   "videos": [
    {
     "author": "dr.derm.love",
     "platform": "TT",
     "views": 1200000,
     "views_hr": 13330,
     "tier": "superviral",
     "x_baseline": 231.1,
     "breakout": "1%",
     "growth": null,
     "eng_top": null,
     "age_days": 3.8,
     "duration_s": 5,
     "caption": "Skin cancer or not? Skin tag, melanoma, seborrheic keratosis #melanoma #seborrheickeratosis #fyp",
     "url": "https://www.tiktok.com/@dr.derm.love/video/7659477254749031710",
     "is_abby": false
    },
    {
     "author": "dr.derm.love",
     "platform": "TT",
     "views": 536200,
     "views_hr": 16847,
     "tier": "superviral",
     "x_baseline": 103.3,
     "breakout": "1%",
     "growth": null,
     "eng_top": null,
     "age_days": 1.4,
     "duration_s": 5,
     "caption": "Skin cancer or not? Melanoma, sk, keloid #melanoma #skincancer #keloid",
     "url": "https://www.tiktok.com/@dr.derm.love/video/7660376990884711710",
     "is_abby": false
    },
    {
     "author": "dr.derm.love",
     "platform": "TT",
     "views": 2200000,
     "views_hr": 13901,
     "tier": "superviral",
     "x_baseline": 423.7,
     "breakout": "1%",
     "growth": null,
     "eng_top": null,
     "age_days": 11.6,
     "duration_s": 5,
     "caption": "Skin cancer or not? Bcc, dermatofibroma, melanoma #skincancer #melanoma #bcc #fyp",
     "url": "https://www.tiktok.com/@dr.derm.love/video/7656566753484393759",
     "is_abby": false
    },
    {
     "author": "dr.derm.love",
     "platform": "TT",
     "views": 934400,
     "views_hr": 8435,
     "tier": "viral",
     "x_baseline": 180.0,
     "breakout": "5%",
     "growth": "silver",
     "eng_top": 49,
     "age_days": 4.7,
     "duration_s": 5,
     "caption": "Is it skin cancer or not? Melanoma, skin tag, melanoma #melanoma #skincancer #melanomaawareness",
     "url": "https://www.tiktok.com/@dr.derm.love/video/7659156362072542494",
     "is_abby": false
    }
   ],
   "her_coverage": {
    "status": "green",
    "summary": "(IG) her BCC-vs-melanoma explainer posted 2d ago — 306K in 2.0d and still climbing (early); library: BCC ultimate guide (YT) 493K, 10 warning signs (YT) Feb 2026",
    "links": [
     {
      "label": "her BCC-vs-melanoma · 306K in 2d",
      "url": "https://www.instagram.com/p/DaiLHGVjy7z/"
     },
     {
      "label": "her BCC ultimate guide (YT) · 493K",
      "url": "https://www.youtube.com/watch?v=58XvGY2s6JQ"
     }
    ]
   },
   "corpus_position": "Basal cell carcinoma usually presents as a shiny pimple that doesn't heal after 6-8 weeks and may even bleed; while melanomas can be raised, most melanomas are flat.",
   "winning_length": "5s three-lesion A/B/C quizzes",
   "angles": [
    {
     "angle": "5s is-it-skin-cancer quiz from her own case photos",
     "grounded": "yes",
     "source": "corpus",
     "verify": false
    },
    {
     "angle": "quiz for reach, 15s ugly-duckling answer for follows",
     "grounded": "yes",
     "source": "corpus",
     "verify": false
    },
    {
     "angle": "myth-bust: most melanomas are flat, not raised",
     "grounded": "yes",
     "source": "corpus",
     "verify": false
    }
   ],
   "stitch_refs": []
  },
  {
   "name": "Glass-skin 'filter routine' + drinkable collagen wave",
   "heat": 3,
   "receipt": "YOURS leads: superviral both platforms (2.4M combined, ♥×2) + civilian wave: 2 more SV, 1.4M and rising fast",
   "videos": [
    {
     "author": "drabby6",
     "platform": "TT",
     "views": 1200000,
     "views_hr": 18994,
     "tier": "superviral",
     "x_baseline": 51.1,
     "breakout": "3%",
     "growth": "gold",
     "eng_top": 1,
     "age_days": 2.7,
     "duration_s": 7,
     "caption": "And don’t forget to exfoliate 1-2 times a week! Don’t use a retinoid when pregnant. What's your glass skin care routine? #glassskin #skincare #skincareroutine",
     "url": "https://www.tiktok.com/@drabby6/video/7659893560606477599",
     "is_abby": true
    },
    {
     "author": "skincarewithyuri",
     "platform": "IG",
     "views": 618498,
     "views_hr": 13736,
     "tier": "superviral",
     "x_baseline": 2.7,
     "breakout": "5%",
     "growth": "gold",
     "eng_top": 3,
     "age_days": 1.9,
     "duration_s": 30,
     "caption": "Filter routine💕✨ -olive oil & lemon shot everyday -eat collagen rich foods -find skincare product works on your skin -increase blood circulation in anyways! #GlowUp #glow #filter #flawlessskin",
     "url": "https://www.instagram.com/p/DaiaAbfpI0k/",
     "is_abby": false
    },
    {
     "author": "skincarewithyuri",
     "platform": "IG",
     "views": 315703,
     "views_hr": 24651,
     "tier": "superviral",
     "x_baseline": 1.4,
     "breakout": "1%",
     "growth": null,
     "eng_top": null,
     "age_days": 0.5,
     "duration_s": 15,
     "caption": "The best tasting collagen🍓🥰 [Gelatin mixture] -Combine 1/4 cup beef gelatin& 1/2 cup room temp water [Maple syrup mixture] - Combine 1 cup maple syrup (honey is ok too), 1/2 cup water and 2 tsp vanill",
     "url": "https://www.instagram.com/p/Dal3QYep2ld/",
     "is_abby": false
    },
    {
     "author": "yurileeeee",
     "platform": "TT",
     "views": 421200,
     "views_hr": 3857,
     "tier": "viral",
     "x_baseline": 14.5,
     "breakout": "3%",
     "growth": "silver",
     "eng_top": 37,
     "age_days": 4.6,
     "duration_s": 26,
     "caption": "Complements in Korea🇰🇷 hits different✨🥹 #glowyskin #glassskin #facemist #summermist",
     "url": "https://www.tiktok.com/@yurileeeee/video/7659185564792409357",
     "is_abby": false
    }
   ],
   "her_coverage": {
    "status": "green",
    "summary": "(IG/TT) YOURS — glass-skin routine superviral this week: 1.2M TT (♥ gold, top-1% engagement) + 1.2M IG (♥ silver) in 2.7d; glass-skin hacks (TT 2023) 485K; collagen supplements explainer (TT Apr 2024) 30K",
    "links": [
     {
      "label": "her glass-skin superviral (TT) · 1.2M in 2.7d",
      "url": "https://www.tiktok.com/@drabby6/video/7659893560606477599"
     },
     {
      "label": "her collagen supplements explainer · 30K",
      "url": "https://www.tiktok.com/@drabby6/video/7363443935806754094"
     }
    ]
   },
   "corpus_position": "Exfoliate 1-2 times a week. Don't use a retinoid when pregnant — retinol/adapalene or azelaic acid at night can be used instead of tretinoin.",
   "winning_length": "7-30s routine listicles",
   "angles": [
    {
     "angle": "part 2: pregnancy-safe glass skin — extend the magnet series",
     "grounded": "yes",
     "source": "corpus",
     "verify": false
    },
    {
     "angle": "explain fibroblasts: where skin collagen actually comes from",
     "grounded": "yes",
     "source": "corpus",
     "verify": false
    },
    {
     "angle": "react: olive-oil-and-lemon shots for filter skin",
     "grounded": "needs her take",
     "source": "feed",
     "verify": false
    }
   ],
   "stitch_refs": [
    0,
    1,
    2
   ]
  },
  {
   "name": "Sunscreen-substitution myths & sun-protection habits",
   "heat": 3,
   "receipt": "5 breakouts · 4 creators · 3.5M combined · 'habits over products' framing + diaper-cream-as-SPF debunks",
   "videos": [
    {
     "author": "beautydermmd",
     "platform": "IG",
     "views": 2413700,
     "views_hr": 17028,
     "tier": "superviral",
     "x_baseline": 125.2,
     "breakout": "1%",
     "growth": "gold",
     "eng_top": 22,
     "age_days": 5.9,
     "duration_s": 6,
     "caption": "Not her serum. Not her skincare. HER HABITS. 👀 Sun protection is elite behavior. UPF clothing. Wide-brim hat. Sunglasses. Shade. This is what dermatologists notice first. You should too. ☀️ #dermatolo",
     "url": "https://www.instagram.com/p/DaX_HEcOs-5/",
     "is_abby": false
    },
    {
     "author": "drdrayzday",
     "platform": "TT",
     "views": 270100,
     "views_hr": 7251,
     "tier": "viral",
     "x_baseline": 13.0,
     "breakout": "1%",
     "growth": "gold",
     "eng_top": 9,
     "age_days": 1.6,
     "duration_s": 160,
     "caption": "Diaper rash cream is not sunscreen. Always look for sunscreens that are labeled broad spectrum and with a stated SPF value (ideally 30 or higher). Don’t assume the presence of high concentrations of z",
     "url": "https://www.tiktok.com/@drdrayzday/video/7660294422763998478",
     "is_abby": false
    },
    {
     "author": "dr.derm.love",
     "platform": "TT",
     "views": 492200,
     "views_hr": 5459,
     "tier": "viral",
     "x_baseline": 94.8,
     "breakout": null,
     "growth": "silver",
     "eng_top": 30,
     "age_days": 3.8,
     "duration_s": 6,
     "caption": "Anne Hathaway knows the way! #annehathaway #sunprotection #spf",
     "url": "https://www.tiktok.com/@dr.derm.love/video/7659475062952594719",
     "is_abby": false
    },
    {
     "author": "drspf",
     "platform": "TT",
     "views": 134700,
     "views_hr": 2234,
     "tier": "viral",
     "x_baseline": 12.0,
     "breakout": "3%",
     "growth": "silver",
     "eng_top": 47,
     "age_days": 2.6,
     "duration_s": 103,
     "caption": "Tinted sunscreen is NOT just makeup with SPF 👀 I especially love tinted sunscreens for melasma, hyperpigmentation, post-acne marks, and uneven tone because they contain iron oxides, which can help pro",
     "url": "https://www.tiktok.com/@drspf/video/7659939596171480351",
     "is_abby": false
    }
   ],
   "her_coverage": {
    "status": "green",
    "summary": "(IG) bemotrizinol sunscreen explainer 7.6d ago — 308K; library: tanning-through-sunscreen (TT) 2.8M, UV-index reminder (TT) 10.2M — her biggest video",
    "links": [
     {
      "label": "her UV-index reminder · 10.2M",
      "url": "https://www.tiktok.com/@drabby6/video/7517816391630703903"
     },
     {
      "label": "her tanning-through-sunscreen · 2.8M",
      "url": "https://www.tiktok.com/@drabby6/video/7492530557419539743"
     }
    ]
   },
   "corpus_position": "UVA is the longer wavelength responsible for tanning and signs of aging — tanning means UVA damage, even wearing sunscreen.",
   "winning_length": "6-8s habit flexes AND 75-160s debunk explainers — both winning",
   "angles": [
    {
     "angle": "her habits, not her serum: UPF-and-shade flex video",
     "grounded": "yes",
     "source": "corpus",
     "verify": false
    },
    {
     "angle": "debunk diaper-cream-as-sunscreen: barrier zinc isn't tested SPF",
     "grounded": "needs her take",
     "source": "feed",
     "verify": false
    },
    {
     "angle": "UV-index reminder rerun: summer-weekend edition",
     "grounded": "yes",
     "source": "corpus",
     "verify": false
    }
   ],
   "stitch_refs": []
  },
  {
   "name": "Derm-rates tier lists — 'worth every penny' / bad-better-best",
   "heat": 3,
   "receipt": "6+ breakouts · 5 creators · 8M+ combined · same rating format everywhere — format signal worth stealing",
   "videos": [
    {
     "author": "dermatologysurgeon",
     "platform": "IG",
     "views": 3433095,
     "views_hr": 24241,
     "tier": "superviral",
     "x_baseline": 4.8,
     "breakout": null,
     "growth": null,
     "eng_top": null,
     "age_days": 5.9,
     "duration_s": 28,
     "caption": "dermatologist rates viral skincare trends 👀 dry brushing (2/10): damages the skin barrier and can cause irritation and tears. use a gentle chemical exfoliant instead putting diaper cream on your face ",
     "url": "https://www.instagram.com/p/DaYAbHaRaAr/",
     "is_abby": false
    },
    {
     "author": "dermguru",
     "platform": "TT",
     "views": 1100000,
     "views_hr": 12173,
     "tier": "superviral",
     "x_baseline": 35.0,
     "breakout": "3%",
     "growth": "gold",
     "eng_top": 5,
     "age_days": 3.8,
     "duration_s": 8,
     "caption": "Worth every penny 💵 #dermatologist",
     "url": "https://www.tiktok.com/@dermguru/video/7659471945418771743",
     "is_abby": false
    },
    {
     "author": "shereeneidriss",
     "platform": "IG",
     "views": 294250,
     "views_hr": 14113,
     "tier": "superviral",
     "x_baseline": 0.9,
     "breakout": "5%",
     "growth": null,
     "eng_top": null,
     "age_days": 0.9,
     "duration_s": 9,
     "caption": "Products (& procedures) worth your hard earned money 🙌 *not sponsored, just worth it",
     "url": "https://www.instagram.com/p/Dak_conu5tQ/",
     "is_abby": false
    },
    {
     "author": "dermatologist_adel",
     "platform": "IG",
     "views": 757092,
     "views_hr": 5389,
     "tier": "viral",
     "x_baseline": 5.9,
     "breakout": null,
     "growth": null,
     "eng_top": null,
     "age_days": 5.9,
     "duration_s": 82,
     "caption": "cheap shit that ACTUALLY works! 🤩 should we do a part 2? 👀 #beautyproducts #haircareroutine #musthaves #productreview #hygienetips @theordinary @saltair @pantene @qandaskin",
     "url": "https://www.instagram.com/p/DaYIUT5xeMj/",
     "is_abby": false
    }
   ],
   "her_coverage": {
    "status": "green",
    "summary": "(IG) her bad-better-best ratings posted 4.6d ago — 125K; library: under-$10 staples (TT 2024) 57K, budget anti-aging routine (YT) Feb 2026",
    "links": [
     {
      "label": "her under-$10 staples · 57K",
      "url": "https://www.tiktok.com/@drabby6/video/7401274994967235882"
     },
     {
      "label": "her budget anti-aging routine (YT)",
      "url": "https://www.youtube.com/watch?v=-dVEzbTKmII"
     }
    ]
   },
   "corpus_position": "These less-than-$10 skincare products are staples in my house — diaper creams with zinc oxide help almost any rash you can imagine.",
   "winning_length": "8-30s rapid tier lists; 60-90s rate-the-trends",
   "angles": [
    {
     "angle": "worth-every-penny: Mohs surgeon edition (scar care, SPF)",
     "grounded": "yes",
     "source": "corpus",
     "verify": false
    },
    {
     "angle": "bad-better-best part 2 — commenters pick the category",
     "grounded": "yes",
     "source": "corpus",
     "verify": false
    },
    {
     "angle": "rate the viral trends: dry-brushing, hypochlorous, tick tools",
     "grounded": "needs her take",
     "source": "feed",
     "verify": false
    }
   ],
   "stitch_refs": []
  }
 ],
 "more_topics": [
  {
   "topic": "doctors' 'never let my own kids' lists",
   "heat": 2,
   "platform": "IG",
   "receipt": "1% breakout, ♥ gold · @teawithmd · 571K in 0.8d (30K/hr)",
   "url": "https://www.instagram.com/p/DalKr5PgSm1/",
   "note": "fastest-rising derm-adjacent format; her tanning-bed corpus fits a derm-mom version"
  },
  {
   "topic": "petroleum jelly: friend or foe",
   "heat": 2,
   "platform": "YT",
   "receipt": "1075× monster, ♥ gold · @Dr. Scott Walter MD · 3.6M in 10.8d",
   "url": "https://www.youtube.com/shorts/RUizJwm0UeA",
   "note": "aging monster but fresh echoes (dr.david.kim 3 vaseline uses, 189K in 0.9d); her slugging position: pea-sized amount"
  },
  {
   "topic": "summer body-odor fixes",
   "heat": 2,
   "platform": "IG",
   "receipt": "5% breakout, ♥ silver · @dermguru · 368K in 1.0d",
   "url": "https://www.instagram.com/p/DakmrWHRdXz/",
   "note": "seasonal; comment-gated DM format driving engagement"
  },
  {
   "topic": "cold-sore science & stigma",
   "heat": 1,
   "platform": "TT",
   "receipt": "304×, 1% · @drspf · 3.4M in 11.8d",
   "url": "https://www.tiktok.com/@drspf/video/7656502031967980830",
   "note": "11.8d — saturated; evergreen stigma-free educational angle only"
  },
  {
   "topic": "melasma & dark-spot tips",
   "heat": 1,
   "platform": "TT",
   "receipt": "477×, 1% · @dermdocmalik · 1.0M in 9.5d",
   "url": "https://www.tiktok.com/@dermdocmalik/video/7657359644507065631",
   "note": "format: one-line 'the more ya know' tip; 9.5d old"
  },
  {
   "topic": "torn-earlobe repair",
   "heat": 1,
   "platform": "IG",
   "receipt": "@denverskindoc stitch · 475K in 3.6d",
   "url": "https://www.instagram.com/p/DaeBcRbhz6E/",
   "note": "procedure lane — Mohs-surgeon credibility play"
  }
 ],
 "her_wins": [
  {
   "summary": "(IG/TT) glass-skin routine — SUPERVIRAL BOTH PLATFORMS and a follower magnet: 1.2M TT in 2.7d (♥ GOLD, top-1% engagement of her 6-month history, 51× baseline, 3% breakout) + 1.2M IG (♥ silver)",
   "platform": "IG/TT",
   "age_days": 2.7,
   "growth": "gold",
   "eng_top": 1,
   "url": "https://www.tiktok.com/@drabby6/video/7659893560606477599",
   "open_lane": "extend the magnet, don't pivot: part 2 pregnancy-safe version, then the 'your glass-skin questions answered' follow-up the comments are seeding"
  },
  {
   "summary": "(IG) BCC-vs-melanoma explainer — 306K in 2.0d, flagged early and still climbing (6.5K/hr)",
   "platform": "IG",
   "age_days": 2.0,
   "url": "https://www.instagram.com/p/DaiLHGVjy7z/",
   "open_lane": "cross-post to TT while it climbs + cut the 5s quiz variant (theme 1's winning format)"
  }
 ],
 "stitch_shortlist": [
  {
   "author": "@skincarewithyuri",
   "platform": "IG",
   "claim": "daily olive-oil-lemon shots + collagen foods = filter skin",
   "views": 618498,
   "age_days": 1.9,
   "comments": 156,
   "comment_heat": false,
   "heat": 2,
   "url": "https://www.instagram.com/p/DaiaAbfpI0k/",
   "seed_topic": "skincare",
   "source": "in-group",
   "verify": false,
   "growth": "gold",
   "eng_top": 3,
   "rubric": {
    "specific_claim": true,
    "her_lane": true,
    "trigger": "half-right",
    "rising": true,
    "big_enough": true,
    "punches_ok": true,
    "score": 6
   },
   "pitch": {
    "the_claim": "Drink an olive-oil-and-lemon shot every day and eat collagen-rich foods and your skin looks like a filter.",
    "why_it_stitches": "SV tier, 5% breakout, ♥ gold (326K/day pace, flagged early) — a diet-fixes-skin claim her audience is already asking about",
    "your_fit": "covered: collagen-supplements explainer (TT Apr 2024) + her OWN glass-skin routine is superviral this week — collide her real routine with the wishful one; verdict on oral collagen needs her take on camera",
    "angles": [
     "empathy-first: love the goal — here's what actually builds collagen",
     "'you want me to WHAT?': drink olive oil daily?",
     "switch-don't-quit: keep the diet, add the retinoid + SPF"
    ],
    "length": "original eats ~5-10s; 30-45s total (short listicles winning this wave)"
   }
  },
  {
   "author": "@skincarewithyuri",
   "platform": "IG",
   "claim": "homemade beef-gelatin + maple gummies = 'best tasting collagen'",
   "views": 315703,
   "age_days": 0.5,
   "comments": 46,
   "comment_heat": false,
   "heat": 1,
   "url": "https://www.instagram.com/p/Dal3QYep2ld/",
   "seed_topic": "skincare",
   "source": "in-group",
   "verify": false,
   "rubric": {
    "specific_claim": true,
    "her_lane": true,
    "trigger": "half-right",
    "rising": true,
    "big_enough": true,
    "punches_ok": true,
    "score": 6
   },
   "pitch": {
    "the_claim": "DIY beef-gelatin gummy recipe as your daily collagen for skin.",
    "why_it_stitches": "fastest riser in the feed — 315K in 0.5d (24.6K/hr, 1% breakout, 631K/day pace); same creator driving the filter-routine wave",
    "your_fit": "her collagen-supplements explainer (Apr 2024) covers the science; the gelatin-vs-hydrolyzed-collagen distinction needs her take on camera",
    "angles": [
     "'you want me to WHAT?': gummy bears as skincare?",
     "explain fibroblasts: eating collagen isn't applying collagen"
    ],
    "length": "original eats ~5-8s; 30-45s total"
   }
  },
  {
   "author": "@skincarewithyuri",
   "platform": "IG",
   "claim": "constant face-misting for glass-skin glow ('compliments in Korea')",
   "views": 630108,
   "age_days": 4.9,
   "comments": 195,
   "comment_heat": false,
   "heat": 1,
   "url": "https://www.instagram.com/p/DaawHdsJ8LO/",
   "seed_topic": "glass skin",
   "source": "in-group",
   "verify": false,
   "rubric": {
    "specific_claim": true,
    "her_lane": true,
    "trigger": "half-right",
    "rising": false,
    "big_enough": true,
    "punches_ok": true,
    "score": 5
   },
   "pitch": {
    "the_claim": "Misting your face all day is the secret to glowing glass skin.",
    "why_it_stitches": "1.05M combined across IG+TT (TT version 3% breakout, ♥ silver, 421K in 4.6d); rubric miss recorded honestly: 4.9d — past the <4d rising bar",
    "your_fit": "no mist position in her corpus — needs her take (classic derm teaching point: water evaporation without an occlusive can dry skin out)",
    "angles": [
     "half-right: mist feels great — here's what it can't do",
     "switch-don't-quit: mist, then SEAL it"
    ],
    "length": "original eats ~5s; 20-30s total"
   }
  }
 ],
 "more_stitches": [
  {
   "author": "@ninaghoulina",
   "platform": "TT",
   "claim": "viral 'She said TRY so I did' makeup-hack demo — exact hack unidentifiable from caption; watch in-app before pitching",
   "views": 4600000,
   "age_days": 2.8,
   "comments": 11900,
   "comment_heat": true,
   "heat": 2,
   "url": "https://www.tiktok.com/@ninaghoulina/video/7659849052653145375",
   "seed_topic": "viral makeup",
   "source": "in-group",
   "verify": false,
   "viral": true,
   "growth": "gold",
   "eng_top": 5,
   "rubric": {
    "specific_claim": false,
    "her_lane": "borderline",
    "trigger": "unknown",
    "rising": true,
    "big_enough": true,
    "punches_ok": true,
    "score": 3
   },
   "pitch": {
    "the_claim": "Unverified makeup-application hack (165s demo, 4.6M in 2.8d, ♥ gold; also 646K on IG; creator posted a 'just clarifying' follow-up — controversy signal).",
    "why_it_stitches": "lane doubt stated: makeup-on-skin, no explicit skin-health claim visible from feed — stitch only if the hack touches skin barrier/acne territory",
    "your_fit": "",
    "angles": [
     "derm-checks-the-viral-hack if a skin claim emerges on watch"
    ],
    "length": "original eats ~10s"
   }
  },
  {
   "author": "@dermdoctor",
   "platform": "TT",
   "claim": "content unidentifiable from feed (caption is a World Cup framing, 203s) — watch in-app first",
   "views": 2500000,
   "age_days": 1.5,
   "comments": 6599,
   "comment_heat": false,
   "heat": 3,
   "url": "https://www.tiktok.com/@dermdoctor/video/7660342475894164766",
   "seed_topic": "dermatologist",
   "source": "in-group",
   "verify": false,
   "viral": true,
   "unidentified": true,
   "rubric": null,
   "pitch": null
  },
  {
   "author": "@bambidoesbeauty",
   "platform": "IG",
   "claim": "content unidentifiable from feed (joke caption only, 7s) — watch in-app first",
   "views": 773865,
   "age_days": 2.8,
   "comments": 130,
   "comment_heat": false,
   "heat": 1,
   "url": "https://www.instagram.com/p/DagFPoTy8-v/",
   "seed_topic": "beauty",
   "source": "in-group",
   "verify": false,
   "viral": true,
   "unidentified": true,
   "rubric": null,
   "pitch": null
  }
 ],
 "news": []
}